{"NORMAL":{"immune":["GHOST"],"nve":["ROCK","STEEL"],"se":[]},"FIRE":{"immune":[],"nve":["FIRE","WATER","ROCK","DRAGON"],"se":["GRASS","ICE","BUG","STEEL"]},"WATER":{"immune":[],"nve":["WATER","GRASS","DRAGON"],"se":["FIRE","GROUND","ROCK"]},"ELECTRIC":{"immune":["GROUND"],"nve":["ELECTRIC","GRASS","DRAGON"],"se":["WATER","FLYING"]},"GRASS":{"immune":[],"nve":["FIRE","GRASS","POISON","FLYING","BUG","DRAGON","STEEL"],"se":["WATER","GROUND","ROCK"]},"ICE":{"immune":[],"nve":["FIRE","WATER","ICE","STEEL"],"se":["GRASS","GROUND","FLYING","DRAGON"]},"FIGHTING":{"immune":["GHOST"],"nve":["POISON","FLYING","PSYCHIC","BUG","FAIRY"],"se":["NORMAL","ICE","ROCK","DARK","STEEL"]},"POISON":{"immune":["STEEL"],"nve":["POISON","GROUND","ROCK","GHOST"],"se":["GRASS","FAIRY"]},"GROUND":{"immune":["FLYING"],"nve":["GRASS","BUG"],"se":["FIRE","ELECTRIC","POISON","ROCK","STEEL"]},"FLYING":{"immune":[],"nve":["ELECTRIC","ROCK","STEEL"],"se":["GRASS","FIGHTING","BUG"]},"PSYCHIC":{"immune":["DARK"],"nve":["PSYCHIC","STEEL"],"se":["FIGHTING","POISON"]},"BUG":{"immune":[],"nve":["FIRE","FIGHTING","POISON","FLYING","GHOST","STEEL","FAIRY"],"se":["GRASS","PSYCHIC","DARK"]},"ROCK":{"immune":[],"nve":["FIGHTING","GROUND","STEEL"],"se":["FIRE","ICE","FLYING","BUG"]},"GHOST":{"immune":["NORMAL"],"nve":["DARK"],"se":["PSYCHIC","GHOST"]},"DRAGON":{"immune":["FAIRY"],"nve":["STEEL"],"se":["DRAGON"]},"DARK":{"immune":[],"nve":["FIGHTING","DARK","FAIRY"],"se":["PSYCHIC","GHOST"]},"STEEL":{"immune":[],"nve":["FIRE","WATER","ELECTRIC","STEEL"],"se":["ICE","ROCK","FAIRY"]},"FAIRY":{"immune":[],"nve":["FIRE","POISON","STEEL"],"se":["FIGHTING","DRAGON","DARK"]}}